LICENSE
MANIFEST.in
README.md
setup.py
pyunicode/__init__.py
pyunicode/api.py
pyunicode.egg-info/PKG-INFO
pyunicode.egg-info/SOURCES.txt
pyunicode.egg-info/dependency_links.txt
pyunicode.egg-info/top_level.txt