Metadata-Version: 1.1
Name: pyunicode
Version: 0.0.3
Summary: Library to deal with common python unicode handling issues
Home-page: http://github.com/Pixelapse/pyunicode
Author: Pixelapse
Author-email: hello@pixelapse.com
License: The MIT License (MIT)
